stream_tweets/__init__.py
stream_tweets/abstract.py
stream_tweets/exception_handlers.py
stream_tweets/parallel_stream.py
stream_tweets/queue_stream.py
stream_tweets/stream_queue_listener.py
stream_tweets/test/__init__.py
stream_tweets/test/test_queue_stream.py
stream_tweets/test/test_stream_queue_listener.py
stream_tweets-1.0.1.dist-info/METADATA
stream_tweets-1.0.1.dist-info/RECORD
stream_tweets-1.0.1.dist-info/WHEEL
stream_tweets-1.0.1.dist-info/top_level.txt
